{
  "processed_nips": [
    {
      "nip": "196712242025211002",
      "index": 0,
      "timestamp": "2026-01-06 09:18:04",
      "status": "success"
    },
    {
      "nip": "196812012025211013",
      "index": 1,
      "timestamp": "2026-01-06 09:18:19",
      "status": "success"
    },
    {
      "nip": "196906272025211006",
      "index": 2,
      "timestamp": "2026-01-06 09:18:33",
      "status": "success"
    },
    {
      "nip": "196907042025211016",
      "index": 3,
      "timestamp": "2026-01-06 09:18:48",
      "status": "success"
    },
    {
      "nip": "197001022025211014",
      "index": 4,
      "timestamp": "2026-01-06 09:19:02",
      "status": "success"
    },
    {
      "nip": "197006142025211013",
      "index": 5,
      "timestamp": "2026-01-06 09:19:16",
      "status": "success"
    },
    {
      "nip": "197007122024211001",
      "index": 6,
      "timestamp": "2026-01-06 09:19:31",
      "status": "success"
    },
    {
      "nip": "197102032025211012",
      "index": 7,
      "timestamp": "2026-01-06 09:19:45",
      "status": "success"
    },
    {
      "nip": "197108052025211012",
      "index": 8,
      "timestamp": "2026-01-06 09:20:00",
      "status": "success"
    },
    {
      "nip": "197108212025211007",
      "index": 9,
      "timestamp": "2026-01-06 09:20:14",
      "status": "success"
    },
    {
      "nip": "197108272025211012",
      "index": 10,
      "timestamp": "2026-01-06 09:20:29",
      "status": "success"
    },
    {
      "nip": "197111272025211004",
      "index": 11,
      "timestamp": "2026-01-06 09:20:43",
      "status": "success"
    },
    {
      "nip": "197202152025211025",
      "index": 12,
      "timestamp": "2026-01-06 09:20:57",
      "status": "success"
    },
    {
      "nip": "197204022025211015",
      "index": 13,
      "timestamp": "2026-01-06 09:21:12",
      "status": "success"
    },
    {
      "nip": "197205222025211014",
      "index": 14,
      "timestamp": "2026-01-06 09:21:26",
      "status": "success"
    },
    {
      "nip": "197208062025211019",
      "index": 15,
      "timestamp": "2026-01-06 09:21:41",
      "status": "success"
    },
    {
      "nip": "197208162025212007",
      "index": 16,
      "timestamp": "2026-01-06 09:21:55",
      "status": "success"
    },
    {
      "nip": "197211082023211004",
      "index": 17,
      "timestamp": "2026-01-06 09:22:09",
      "status": "success"
    },
    {
      "nip": "197212142025211011",
      "index": 18,
      "timestamp": "2026-01-06 09:22:24",
      "status": "success"
    },
    {
      "nip": "197301062025211007",
      "index": 19,
      "timestamp": "2026-01-06 09:22:38",
      "status": "success"
    },
    {
      "nip": "197301282025212007",
      "index": 20,
      "timestamp": "2026-01-06 09:22:53",
      "status": "success"
    },
    {
      "nip": "197302022025211015",
      "index": 21,
      "timestamp": "2026-01-06 09:23:07",
      "status": "success"
    },
    {
      "nip": "197305122025211037",
      "index": 22,
      "timestamp": "2026-01-06 09:23:21",
      "status": "success"
    },
    {
      "nip": "197309252025211012",
      "index": 23,
      "timestamp": "2026-01-06 09:23:36",
      "status": "success"
    },
    {
      "nip": "197312232025211009",
      "index": 24,
      "timestamp": "2026-01-06 09:23:50",
      "status": "success"
    },
    {
      "nip": "197404252025211014",
      "index": 25,
      "timestamp": "2026-01-06 09:24:05",
      "status": "success"
    },
    {
      "nip": "197405172025211017",
      "index": 26,
      "timestamp": "2026-01-06 09:24:19",
      "status": "success"
    },
    {
      "nip": "197408162025211012",
      "index": 27,
      "timestamp": "2026-01-06 09:24:33",
      "status": "success"
    },
    {
      "nip": "197408212025211007",
      "index": 28,
      "timestamp": "2026-01-06 09:24:48",
      "status": "success"
    },
    {
      "nip": "197409282025211010",
      "index": 29,
      "timestamp": "2026-01-06 09:25:02",
      "status": "success"
    },
    {
      "nip": "197412312025211059",
      "index": 30,
      "timestamp": "2026-01-06 09:25:17",
      "status": "success"
    },
    {
      "nip": "197502072025211008",
      "index": 31,
      "timestamp": "2026-01-06 09:25:31",
      "status": "success"
    },
    {
      "nip": "197502212025211010",
      "index": 32,
      "timestamp": "2026-01-06 09:25:45",
      "status": "success"
    },
    {
      "nip": "197503122025211024",
      "index": 33,
      "timestamp": "2026-01-06 09:26:00",
      "status": "success"
    },
    {
      "nip": "197505012025211015",
      "index": 34,
      "timestamp": "2026-01-06 09:26:14",
      "status": "success"
    },
    {
      "nip": "197505302025211004",
      "index": 35,
      "timestamp": "2026-01-06 09:26:29",
      "status": "success"
    },
    {
      "nip": "197511042025211009",
      "index": 36,
      "timestamp": "2026-01-06 09:26:43",
      "status": "success"
    },
    {
      "nip": "197512022025212013",
      "index": 37,
      "timestamp": "2026-01-06 09:26:57",
      "status": "success"
    },
    {
      "nip": "197512072025211017",
      "index": 38,
      "timestamp": "2026-01-06 09:27:12",
      "status": "success"
    },
    {
      "nip": "197512102025211014",
      "index": 39,
      "timestamp": "2026-01-06 09:27:26",
      "status": "success"
    },
    {
      "nip": "197603212023211003",
      "index": 40,
      "timestamp": "2026-01-06 09:27:41",
      "status": "success"
    },
    {
      "nip": "197603232025212010",
      "index": 41,
      "timestamp": "2026-01-06 09:27:55",
      "status": "success"
    },
    {
      "nip": "197609112025211023",
      "index": 42,
      "timestamp": "2026-01-06 09:28:09",
      "status": "success"
    },
    {
      "nip": "197609242025212006",
      "index": 43,
      "timestamp": "2026-01-06 09:28:24",
      "status": "success"
    },
    {
      "nip": "197609252025211008",
      "index": 44,
      "timestamp": "2026-01-06 09:28:38",
      "status": "success"
    },
    {
      "nip": "197611222025211008",
      "index": 45,
      "timestamp": "2026-01-06 09:28:53",
      "status": "success"
    },
    {
      "nip": "197612102025211015",
      "index": 46,
      "timestamp": "2026-01-06 09:29:07",
      "status": "success"
    },
    {
      "nip": "197701132025211012",
      "index": 47,
      "timestamp": "2026-01-06 09:29:21",
      "status": "success"
    },
    {
      "nip": "197703162025211022",
      "index": 48,
      "timestamp": "2026-01-06 09:29:36",
      "status": "success"
    },
    {
      "nip": "197703232025212016",
      "index": 49,
      "timestamp": "2026-01-06 09:29:50",
      "status": "success"
    },
    {
      "nip": "197706272025211022",
      "index": 50,
      "timestamp": "2026-01-06 09:30:05",
      "status": "success"
    },
    {
      "nip": "197706282025211004",
      "index": 51,
      "timestamp": "2026-01-06 09:30:19",
      "status": "success"
    },
    {
      "nip": "197708312025211007",
      "index": 52,
      "timestamp": "2026-01-06 09:30:33",
      "status": "success"
    },
    {
      "nip": "197709062025211009",
      "index": 53,
      "timestamp": "2026-01-06 09:30:48",
      "status": "success"
    },
    {
      "nip": "197711152025211018",
      "index": 54,
      "timestamp": "2026-01-06 09:31:02",
      "status": "success"
    },
    {
      "nip": "197801032024211001",
      "index": 55,
      "timestamp": "2026-01-06 09:31:17",
      "status": "success"
    },
    {
      "nip": "197802202025211010",
      "index": 56,
      "timestamp": "2026-01-06 09:31:31",
      "status": "success"
    },
    {
      "nip": "197803092025211025",
      "index": 57,
      "timestamp": "2026-01-06 09:31:45",
      "status": "success"
    },
    {
      "nip": "197803222025211019",
      "index": 58,
      "timestamp": "2026-01-06 09:32:00",
      "status": "success"
    },
    {
      "nip": "197806262025211013",
      "index": 60,
      "timestamp": "2026-01-06 09:32:29",
      "status": "success"
    },
    {
      "nip": "197806272025211023",
      "index": 61,
      "timestamp": "2026-01-06 09:32:43",
      "status": "success"
    },
    {
      "nip": "197809082025211015",
      "index": 62,
      "timestamp": "2026-01-06 09:32:58",
      "status": "success"
    },
    {
      "nip": "197809212025211014",
      "index": 63,
      "timestamp": "2026-01-06 09:33:12",
      "status": "success"
    },
    {
      "nip": "197810292025212006",
      "index": 64,
      "timestamp": "2026-01-06 09:33:26",
      "status": "success"
    },
    {
      "nip": "197811072025211019",
      "index": 65,
      "timestamp": "2026-01-06 09:33:41",
      "status": "success"
    },
    {
      "nip": "197811132025211011",
      "index": 66,
      "timestamp": "2026-01-06 09:33:55",
      "status": "success"
    },
    {
      "nip": "197811252025211015",
      "index": 67,
      "timestamp": "2026-01-06 09:34:10",
      "status": "success"
    },
    {
      "nip": "197811262025211009",
      "index": 68,
      "timestamp": "2026-01-06 09:34:24",
      "status": "success"
    },
    {
      "nip": "197901042025211020",
      "index": 69,
      "timestamp": "2026-01-06 09:34:38",
      "status": "success"
    },
    {
      "nip": "197904092025211014",
      "index": 70,
      "timestamp": "2026-01-06 09:34:53",
      "status": "success"
    },
    {
      "nip": "197905112025211018",
      "index": 71,
      "timestamp": "2026-01-06 09:35:07",
      "status": "success"
    },
    {
      "nip": "197905242025212009",
      "index": 72,
      "timestamp": "2026-01-06 09:35:22",
      "status": "success"
    },
    {
      "nip": "197906162025211020",
      "index": 74,
      "timestamp": "2026-01-06 09:35:51",
      "status": "success"
    },
    {
      "nip": "197906302025211021",
      "index": 76,
      "timestamp": "2026-01-06 09:36:20",
      "status": "success"
    },
    {
      "nip": "197909132025211012",
      "index": 77,
      "timestamp": "2026-01-06 09:36:34",
      "status": "success"
    },
    {
      "nip": "197910012025212014",
      "index": 78,
      "timestamp": "2026-01-06 09:36:48",
      "status": "success"
    },
    {
      "nip": "197910042025211013",
      "index": 79,
      "timestamp": "2026-01-06 09:37:03",
      "status": "success"
    },
    {
      "nip": "197912212025211013",
      "index": 80,
      "timestamp": "2026-01-06 09:37:17",
      "status": "success"
    },
    {
      "nip": "198001102025211019",
      "index": 81,
      "timestamp": "2026-01-06 09:37:32",
      "status": "success"
    },
    {
      "nip": "198009242025212012",
      "index": 92,
      "timestamp": "2026-01-06 09:40:55",
      "status": "success"
    },
    {
      "nip": "198010222025211021",
      "index": 93,
      "timestamp": "2026-01-06 09:41:10",
      "status": "success"
    },
    {
      "nip": "198011162025211014",
      "index": 94,
      "timestamp": "2026-01-06 09:41:24",
      "status": "success"
    },
    {
      "nip": "198011202025211018",
      "index": 95,
      "timestamp": "2026-01-06 09:41:39",
      "status": "success"
    },
    {
      "nip": "198101052025211039",
      "index": 96,
      "timestamp": "2026-01-06 09:41:53",
      "status": "success"
    },
    {
      "nip": "198101082025211014",
      "index": 97,
      "timestamp": "2026-01-06 09:42:07",
      "status": "success"
    },
    {
      "nip": "198104022025211029",
      "index": 98,
      "timestamp": "2026-01-06 09:42:22",
      "status": "success"
    },
    {
      "nip": "198104242025211022",
      "index": 99,
      "timestamp": "2026-01-06 09:42:36",
      "status": "success"
    },
    {
      "nip": "198104262025211019",
      "index": 100,
      "timestamp": "2026-01-06 09:42:51",
      "status": "success"
    },
    {
      "nip": "198105102025211048",
      "index": 101,
      "timestamp": "2026-01-06 09:43:05",
      "status": "success"
    },
    {
      "nip": "198105112025211020",
      "index": 102,
      "timestamp": "2026-01-06 09:43:19",
      "status": "success"
    },
    {
      "nip": "198105132025211034",
      "index": 103,
      "timestamp": "2026-01-06 09:43:34",
      "status": "success"
    },
    {
      "nip": "198106262025211016",
      "index": 104,
      "timestamp": "2026-01-06 09:43:48",
      "status": "success"
    },
    {
      "nip": "198107082025211022",
      "index": 105,
      "timestamp": "2026-01-06 09:44:03",
      "status": "success"
    },
    {
      "nip": "198109202025211015",
      "index": 106,
      "timestamp": "2026-01-06 09:44:17",
      "status": "success"
    },
    {
      "nip": "198109252025211015",
      "index": 107,
      "timestamp": "2026-01-06 09:44:31",
      "status": "success"
    },
    {
      "nip": "198110012025211019",
      "index": 108,
      "timestamp": "2026-01-06 09:44:46",
      "status": "success"
    },
    {
      "nip": "198112092025211012",
      "index": 109,
      "timestamp": "2026-01-06 09:45:00",
      "status": "success"
    },
    {
      "nip": "198112292025211017",
      "index": 110,
      "timestamp": "2026-01-06 09:45:15",
      "status": "success"
    },
    {
      "nip": "198201252025211015",
      "index": 111,
      "timestamp": "2026-01-06 09:45:29",
      "status": "success"
    },
    {
      "nip": "198204132025211020",
      "index": 112,
      "timestamp": "2026-01-06 09:45:43",
      "status": "success"
    },
    {
      "nip": "198204192025211026",
      "index": 113,
      "timestamp": "2026-01-06 09:45:58",
      "status": "success"
    },
    {
      "nip": "198205242025211011",
      "index": 114,
      "timestamp": "2026-01-06 09:46:12",
      "status": "success"
    },
    {
      "nip": "198205312025211018",
      "index": 115,
      "timestamp": "2026-01-06 09:46:27",
      "status": "success"
    },
    {
      "nip": "198207252025212023",
      "index": 116,
      "timestamp": "2026-01-06 09:46:41",
      "status": "success"
    },
    {
      "nip": "198208062025211035",
      "index": 117,
      "timestamp": "2026-01-06 09:46:55",
      "status": "success"
    },
    {
      "nip": "198209042025211018",
      "index": 118,
      "timestamp": "2026-01-06 09:47:10",
      "status": "success"
    },
    {
      "nip": "198209272025212018",
      "index": 119,
      "timestamp": "2026-01-06 09:47:24",
      "status": "success"
    },
    {
      "nip": "198211132025211013",
      "index": 120,
      "timestamp": "2026-01-06 09:47:39",
      "status": "success"
    },
    {
      "nip": "198212032025212013",
      "index": 121,
      "timestamp": "2026-01-06 09:47:53",
      "status": "success"
    },
    {
      "nip": "198212312025211043",
      "index": 122,
      "timestamp": "2026-01-06 09:48:07",
      "status": "success"
    },
    {
      "nip": "198302282025211037",
      "index": 123,
      "timestamp": "2026-01-06 09:48:22",
      "status": "success"
    },
    {
      "nip": "198303032025211041",
      "index": 124,
      "timestamp": "2026-01-06 09:48:36",
      "status": "success"
    },
    {
      "nip": "198303112025212016",
      "index": 125,
      "timestamp": "2026-01-06 09:48:51",
      "status": "success"
    },
    {
      "nip": "198304072025211048",
      "index": 126,
      "timestamp": "2026-01-06 09:49:05",
      "status": "success"
    },
    {
      "nip": "198304192025211021",
      "index": 127,
      "timestamp": "2026-01-06 09:49:19",
      "status": "success"
    },
    {
      "nip": "198304202025211032",
      "index": 128,
      "timestamp": "2026-01-06 09:49:34",
      "status": "success"
    },
    {
      "nip": "198306022025211033",
      "index": 129,
      "timestamp": "2026-01-06 09:49:48",
      "status": "success"
    },
    {
      "nip": "198306072025211047",
      "index": 130,
      "timestamp": "2026-01-06 09:50:03",
      "status": "success"
    },
    {
      "nip": "198309132025211020",
      "index": 131,
      "timestamp": "2026-01-06 09:50:17",
      "status": "success"
    },
    {
      "nip": "198309262025211015",
      "index": 132,
      "timestamp": "2026-01-06 09:50:31",
      "status": "success"
    },
    {
      "nip": "198310112025211021",
      "index": 133,
      "timestamp": "2026-01-06 09:50:46",
      "status": "success"
    },
    {
      "nip": "198311152025211021",
      "index": 134,
      "timestamp": "2026-01-06 09:51:00",
      "status": "success"
    },
    {
      "nip": "198312032025211011",
      "index": 135,
      "timestamp": "2026-01-06 09:51:15",
      "status": "success"
    },
    {
      "nip": "198401132025212010",
      "index": 136,
      "timestamp": "2026-01-06 09:51:29",
      "status": "success"
    },
    {
      "nip": "198401152025211016",
      "index": 137,
      "timestamp": "2026-01-06 09:51:43",
      "status": "success"
    },
    {
      "nip": "198401212024212001",
      "index": 138,
      "timestamp": "2026-01-06 09:51:58",
      "status": "success"
    },
    {
      "nip": "198403172025212035",
      "index": 139,
      "timestamp": "2026-01-06 09:52:12",
      "status": "success"
    },
    {
      "nip": "198403222025211028",
      "index": 140,
      "timestamp": "2026-01-06 09:52:27",
      "status": "success"
    },
    {
      "nip": "198405012025211029",
      "index": 141,
      "timestamp": "2026-01-06 09:52:41",
      "status": "success"
    },
    {
      "nip": "198405062025212014",
      "index": 142,
      "timestamp": "2026-01-06 09:52:55",
      "status": "success"
    },
    {
      "nip": "198405092025211020",
      "index": 143,
      "timestamp": "2026-01-06 09:53:10",
      "status": "success"
    },
    {
      "nip": "198406022025211032",
      "index": 144,
      "timestamp": "2026-01-06 09:53:24",
      "status": "success"
    },
    {
      "nip": "198407172025212041",
      "index": 145,
      "timestamp": "2026-01-06 09:53:39",
      "status": "success"
    },
    {
      "nip": "198409072025212017",
      "index": 146,
      "timestamp": "2026-01-06 09:53:53",
      "status": "success"
    },
    {
      "nip": "198409222025211017",
      "index": 147,
      "timestamp": "2026-01-06 09:54:07",
      "status": "success"
    },
    {
      "nip": "198410082025211024",
      "index": 148,
      "timestamp": "2026-01-06 09:54:22",
      "status": "success"
    },
    {
      "nip": "198411012025211026",
      "index": 149,
      "timestamp": "2026-01-06 09:54:36",
      "status": "success"
    },
    {
      "nip": "198411122025211017",
      "index": 150,
      "timestamp": "2026-01-06 09:54:51",
      "status": "success"
    },
    {
      "nip": "198411242025212017",
      "index": 151,
      "timestamp": "2026-01-06 09:55:05",
      "status": "success"
    },
    {
      "nip": "198411282024211001",
      "index": 152,
      "timestamp": "2026-01-06 09:55:19",
      "status": "success"
    },
    {
      "nip": "198411292025212017",
      "index": 153,
      "timestamp": "2026-01-06 09:55:34",
      "status": "success"
    },
    {
      "nip": "198412242025211019",
      "index": 154,
      "timestamp": "2026-01-06 09:55:48",
      "status": "success"
    },
    {
      "nip": "198412272025212012",
      "index": 155,
      "timestamp": "2026-01-06 09:56:03",
      "status": "success"
    },
    {
      "nip": "198501072025211021",
      "index": 156,
      "timestamp": "2026-01-06 09:56:17",
      "status": "success"
    },
    {
      "nip": "198502282025211016",
      "index": 157,
      "timestamp": "2026-01-06 09:56:31",
      "status": "success"
    },
    {
      "nip": "198503072025211028",
      "index": 158,
      "timestamp": "2026-01-06 09:56:46",
      "status": "success"
    },
    {
      "nip": "198504012025212021",
      "index": 159,
      "timestamp": "2026-01-06 09:57:00",
      "status": "success"
    },
    {
      "nip": "198504082025211022",
      "index": 160,
      "timestamp": "2026-01-06 09:57:15",
      "status": "success"
    },
    {
      "nip": "198504282025211026",
      "index": 161,
      "timestamp": "2026-01-06 09:57:29",
      "status": "success"
    },
    {
      "nip": "198504292025211034",
      "index": 162,
      "timestamp": "2026-01-06 09:57:43",
      "status": "success"
    },
    {
      "nip": "198505012025212021",
      "index": 163,
      "timestamp": "2026-01-06 09:57:58",
      "status": "success"
    },
    {
      "nip": "198506102025211056",
      "index": 164,
      "timestamp": "2026-01-06 09:58:12",
      "status": "success"
    },
    {
      "nip": "198506112025212022",
      "index": 165,
      "timestamp": "2026-01-06 09:58:27",
      "status": "success"
    },
    {
      "nip": "198506122025211046",
      "index": 166,
      "timestamp": "2026-01-06 09:58:41",
      "status": "success"
    },
    {
      "nip": "198506162025211029",
      "index": 167,
      "timestamp": "2026-01-06 09:58:55",
      "status": "success"
    },
    {
      "nip": "198506172025211022",
      "index": 168,
      "timestamp": "2026-01-06 09:59:10",
      "status": "success"
    },
    {
      "nip": "198506242025211022",
      "index": 169,
      "timestamp": "2026-01-06 09:59:24",
      "status": "success"
    },
    {
      "nip": "198506262025211023",
      "index": 170,
      "timestamp": "2026-01-06 09:59:39",
      "status": "success"
    },
    {
      "nip": "198506302025212014",
      "index": 171,
      "timestamp": "2026-01-06 09:59:53",
      "status": "success"
    },
    {
      "nip": "198508052025211039",
      "index": 172,
      "timestamp": "2026-01-06 10:00:07",
      "status": "success"
    },
    {
      "nip": "198509012025212021",
      "index": 173,
      "timestamp": "2026-01-06 10:00:22",
      "status": "success"
    },
    {
      "nip": "198509232024212002",
      "index": 174,
      "timestamp": "2026-01-06 10:00:36",
      "status": "success"
    },
    {
      "nip": "198510022025211035",
      "index": 175,
      "timestamp": "2026-01-06 10:00:51",
      "status": "success"
    },
    {
      "nip": "198510092025211020",
      "index": 176,
      "timestamp": "2026-01-06 10:01:05",
      "status": "success"
    },
    {
      "nip": "198606202025212017",
      "index": 188,
      "timestamp": "2026-01-06 10:06:24",
      "status": "success"
    },
    {
      "nip": "198607262025212017",
      "index": 189,
      "timestamp": "2026-01-06 10:06:39",
      "status": "success"
    },
    {
      "nip": "198608132025212019",
      "index": 190,
      "timestamp": "2026-01-06 10:06:53",
      "status": "success"
    },
    {
      "nip": "198608212025211033",
      "index": 191,
      "timestamp": "2026-01-06 10:07:07",
      "status": "success"
    },
    {
      "nip": "198608312025211024",
      "index": 192,
      "timestamp": "2026-01-06 10:07:22",
      "status": "success"
    },
    {
      "nip": "198609012025212018",
      "index": 193,
      "timestamp": "2026-01-06 10:07:36",
      "status": "success"
    },
    {
      "nip": "198609132025211028",
      "index": 194,
      "timestamp": "2026-01-06 10:07:51",
      "status": "success"
    },
    {
      "nip": "198610092025211040",
      "index": 195,
      "timestamp": "2026-01-06 10:08:05",
      "status": "success"
    },
    {
      "nip": "198611012024211001",
      "index": 196,
      "timestamp": "2026-01-06 10:08:19",
      "status": "success"
    },
    {
      "nip": "198611012025212023",
      "index": 197,
      "timestamp": "2026-01-06 10:08:34",
      "status": "success"
    },
    {
      "nip": "198611232025211044",
      "index": 198,
      "timestamp": "2026-01-06 10:08:48",
      "status": "success"
    },
    {
      "nip": "198612072025211019",
      "index": 199,
      "timestamp": "2026-01-06 10:09:03",
      "status": "success"
    },
    {
      "nip": "198612132025211037",
      "index": 200,
      "timestamp": "2026-01-06 10:09:17",
      "status": "success"
    },
    {
      "nip": "198701202025211029",
      "index": 201,
      "timestamp": "2026-01-06 10:09:31",
      "status": "success"
    },
    {
      "nip": "198702152025211024",
      "index": 203,
      "timestamp": "2026-01-06 10:10:00",
      "status": "success"
    },
    {
      "nip": "198702242025211039",
      "index": 204,
      "timestamp": "2026-01-06 10:10:15",
      "status": "success"
    },
    {
      "nip": "198703122025211029",
      "index": 205,
      "timestamp": "2026-01-06 10:10:29",
      "status": "success"
    },
    {
      "nip": "198703182025211024",
      "index": 206,
      "timestamp": "2026-01-06 10:10:44",
      "status": "success"
    },
    {
      "nip": "198704142025212025",
      "index": 207,
      "timestamp": "2026-01-06 10:10:58",
      "status": "success"
    },
    {
      "nip": "198706172025211042",
      "index": 210,
      "timestamp": "2026-01-06 10:11:43",
      "status": "success"
    },
    {
      "nip": "198707122025211029",
      "index": 211,
      "timestamp": "2026-01-06 10:11:58",
      "status": "success"
    },
    {
      "nip": "198707142025212033",
      "index": 212,
      "timestamp": "2026-01-06 10:12:12",
      "status": "success"
    },
    {
      "nip": "198707212025211031",
      "index": 213,
      "timestamp": "2026-01-06 10:12:26",
      "status": "success"
    },
    {
      "nip": "198708212025212024",
      "index": 214,
      "timestamp": "2026-01-06 10:12:41",
      "status": "success"
    },
    {
      "nip": "198709052025211030",
      "index": 215,
      "timestamp": "2026-01-06 10:12:55",
      "status": "success"
    },
    {
      "nip": "198709092025211031",
      "index": 216,
      "timestamp": "2026-01-06 10:13:09",
      "status": "success"
    },
    {
      "nip": "198709112025211022",
      "index": 217,
      "timestamp": "2026-01-06 10:13:24",
      "status": "success"
    },
    {
      "nip": "198709122025211027",
      "index": 218,
      "timestamp": "2026-01-06 10:13:38",
      "status": "success"
    },
    {
      "nip": "198709122025211028",
      "index": 219,
      "timestamp": "2026-01-06 10:13:53",
      "status": "success"
    },
    {
      "nip": "198709152024211001",
      "index": 220,
      "timestamp": "2026-01-06 10:14:07",
      "status": "success"
    },
    {
      "nip": "198709292025212020",
      "index": 221,
      "timestamp": "2026-01-06 10:14:21",
      "status": "success"
    },
    {
      "nip": "198710282025211031",
      "index": 222,
      "timestamp": "2026-01-06 10:14:36",
      "status": "success"
    },
    {
      "nip": "198711102025211039",
      "index": 223,
      "timestamp": "2026-01-06 10:14:50",
      "status": "success"
    },
    {
      "nip": "198711222025211019",
      "index": 224,
      "timestamp": "2026-01-06 10:15:05",
      "status": "success"
    },
    {
      "nip": "198801032025212023",
      "index": 225,
      "timestamp": "2026-01-06 10:15:19",
      "status": "success"
    },
    {
      "nip": "198801092025212019",
      "index": 226,
      "timestamp": "2026-01-06 10:15:33",
      "status": "success"
    },
    {
      "nip": "198801132025211030",
      "index": 227,
      "timestamp": "2026-01-06 10:15:48",
      "status": "success"
    },
    {
      "nip": "198802252025212019",
      "index": 228,
      "timestamp": "2026-01-06 10:16:02",
      "status": "success"
    },
    {
      "nip": "198803042025211040",
      "index": 229,
      "timestamp": "2026-01-06 10:16:17",
      "status": "success"
    },
    {
      "nip": "198803312025212041",
      "index": 230,
      "timestamp": "2026-01-06 10:16:31",
      "status": "success"
    },
    {
      "nip": "198804282025211050",
      "index": 231,
      "timestamp": "2026-01-06 10:16:45",
      "status": "success"
    },
    {
      "nip": "198805092025212022",
      "index": 232,
      "timestamp": "2026-01-06 10:17:00",
      "status": "success"
    },
    {
      "nip": "198805142025212028",
      "index": 233,
      "timestamp": "2026-01-06 10:17:14",
      "status": "success"
    },
    {
      "nip": "198805172025212024",
      "index": 234,
      "timestamp": "2026-01-06 10:17:29",
      "status": "success"
    },
    {
      "nip": "198805252025211037",
      "index": 235,
      "timestamp": "2026-01-06 10:17:43",
      "status": "success"
    },
    {
      "nip": "198805302025211023",
      "index": 236,
      "timestamp": "2026-01-06 10:17:57",
      "status": "success"
    },
    {
      "nip": "198806172025211025",
      "index": 237,
      "timestamp": "2026-01-06 10:18:12",
      "status": "success"
    },
    {
      "nip": "198806222025212019",
      "index": 238,
      "timestamp": "2026-01-06 10:18:26",
      "status": "success"
    },
    {
      "nip": "198806272025211021",
      "index": 239,
      "timestamp": "2026-01-06 10:18:41",
      "status": "success"
    },
    {
      "nip": "198807122023211020",
      "index": 240,
      "timestamp": "2026-01-06 10:18:55",
      "status": "success"
    },
    {
      "nip": "198807172025211032",
      "index": 241,
      "timestamp": "2026-01-06 10:19:09",
      "status": "success"
    },
    {
      "nip": "198808072025211027",
      "index": 242,
      "timestamp": "2026-01-06 10:19:24",
      "status": "success"
    },
    {
      "nip": "198808082025211041",
      "index": 243,
      "timestamp": "2026-01-06 10:19:38",
      "status": "success"
    },
    {
      "nip": "198809092025211026",
      "index": 244,
      "timestamp": "2026-01-06 10:19:53",
      "status": "success"
    },
    {
      "nip": "198809122025211028",
      "index": 245,
      "timestamp": "2026-01-06 10:20:07",
      "status": "success"
    },
    {
      "nip": "198809132025212026",
      "index": 246,
      "timestamp": "2026-01-06 10:20:21",
      "status": "success"
    },
    {
      "nip": "198810032025211029",
      "index": 247,
      "timestamp": "2026-01-06 10:20:36",
      "status": "success"
    },
    {
      "nip": "198810042025211022",
      "index": 248,
      "timestamp": "2026-01-06 10:20:50",
      "status": "success"
    },
    {
      "nip": "198810152025212018",
      "index": 249,
      "timestamp": "2026-01-06 10:21:04",
      "status": "success"
    },
    {
      "nip": "198810252025211025",
      "index": 250,
      "timestamp": "2026-01-06 10:21:19",
      "status": "success"
    },
    {
      "nip": "198810272025211020",
      "index": 251,
      "timestamp": "2026-01-06 10:21:33",
      "status": "success"
    },
    {
      "nip": "198811102025212031",
      "index": 252,
      "timestamp": "2026-01-06 10:21:48",
      "status": "success"
    },
    {
      "nip": "198812092024212001",
      "index": 253,
      "timestamp": "2026-01-06 10:22:02",
      "status": "success"
    },
    {
      "nip": "198812112025211029",
      "index": 254,
      "timestamp": "2026-01-06 10:22:16",
      "status": "success"
    },
    {
      "nip": "198901082025211019",
      "index": 255,
      "timestamp": "2026-01-06 10:22:31",
      "status": "success"
    },
    {
      "nip": "198901182025212033",
      "index": 256,
      "timestamp": "2026-01-06 10:22:45",
      "status": "success"
    },
    {
      "nip": "198902052025211032",
      "index": 257,
      "timestamp": "2026-01-06 10:23:00",
      "status": "success"
    },
    {
      "nip": "198902072025212020",
      "index": 258,
      "timestamp": "2026-01-06 10:23:14",
      "status": "success"
    },
    {
      "nip": "198902172025212051",
      "index": 259,
      "timestamp": "2026-01-06 10:23:28",
      "status": "success"
    },
    {
      "nip": "198902242025212026",
      "index": 260,
      "timestamp": "2026-01-06 10:23:43",
      "status": "success"
    },
    {
      "nip": "198903162025212026",
      "index": 261,
      "timestamp": "2026-01-06 10:23:57",
      "status": "success"
    },
    {
      "nip": "198904052025211026",
      "index": 262,
      "timestamp": "2026-01-06 10:24:12",
      "status": "success"
    },
    {
      "nip": "198904092025211031",
      "index": 263,
      "timestamp": "2026-01-06 10:24:26",
      "status": "success"
    },
    {
      "nip": "198904172025211063",
      "index": 264,
      "timestamp": "2026-01-06 10:24:40",
      "status": "success"
    },
    {
      "nip": "198904292025212018",
      "index": 265,
      "timestamp": "2026-01-06 10:24:55",
      "status": "success"
    },
    {
      "nip": "198905242025211026",
      "index": 267,
      "timestamp": "2026-01-06 10:25:24",
      "status": "success"
    },
    {
      "nip": "198906042025211021",
      "index": 268,
      "timestamp": "2026-01-06 10:25:38",
      "status": "success"
    },
    {
      "nip": "198906102023211029",
      "index": 269,
      "timestamp": "2026-01-06 10:25:53",
      "status": "success"
    },
    {
      "nip": "198906162025211026",
      "index": 270,
      "timestamp": "2026-01-06 10:26:07",
      "status": "success"
    },
    {
      "nip": "198906172025211027",
      "index": 271,
      "timestamp": "2026-01-06 10:26:21",
      "status": "success"
    },
    {
      "nip": "198906172025211028",
      "index": 272,
      "timestamp": "2026-01-06 10:26:36",
      "status": "success"
    },
    {
      "nip": "198906172025212018",
      "index": 273,
      "timestamp": "2026-01-06 10:26:50",
      "status": "success"
    },
    {
      "nip": "198907042025211026",
      "index": 274,
      "timestamp": "2026-01-06 10:27:05",
      "status": "success"
    },
    {
      "nip": "198907102025212027",
      "index": 275,
      "timestamp": "2026-01-06 10:27:19",
      "status": "success"
    },
    {
      "nip": "198907152025211034",
      "index": 276,
      "timestamp": "2026-01-06 10:27:33",
      "status": "success"
    },
    {
      "nip": "198907262025211021",
      "index": 277,
      "timestamp": "2026-01-06 10:27:48",
      "status": "success"
    },
    {
      "nip": "198907292025211025",
      "index": 278,
      "timestamp": "2026-01-06 10:28:02",
      "status": "success"
    },
    {
      "nip": "198908012025211053",
      "index": 279,
      "timestamp": "2026-01-06 10:28:17",
      "status": "success"
    },
    {
      "nip": "198908172025211050",
      "index": 280,
      "timestamp": "2026-01-06 10:28:31",
      "status": "success"
    },
    {
      "nip": "198908222025212027",
      "index": 281,
      "timestamp": "2026-01-06 10:28:45",
      "status": "success"
    },
    {
      "nip": "198908312025211031",
      "index": 282,
      "timestamp": "2026-01-06 10:29:00",
      "status": "success"
    },
    {
      "nip": "198909012025211020",
      "index": 283,
      "timestamp": "2026-01-06 10:29:14",
      "status": "success"
    },
    {
      "nip": "198910272025211040",
      "index": 284,
      "timestamp": "2026-01-06 10:29:29",
      "status": "success"
    },
    {
      "nip": "198911052025212021",
      "index": 285,
      "timestamp": "2026-01-06 10:29:43",
      "status": "success"
    },
    {
      "nip": "198911062025212029",
      "index": 286,
      "timestamp": "2026-01-06 10:29:57",
      "status": "success"
    },
    {
      "nip": "198911072025211044",
      "index": 287,
      "timestamp": "2026-01-06 10:30:12",
      "status": "success"
    },
    {
      "nip": "198911232025211017",
      "index": 288,
      "timestamp": "2026-01-06 10:30:26",
      "status": "success"
    },
    {
      "nip": "198911252025211043",
      "index": 289,
      "timestamp": "2026-01-06 10:30:41",
      "status": "success"
    },
    {
      "nip": "198911302025211022",
      "index": 290,
      "timestamp": "2026-01-06 10:30:55",
      "status": "success"
    },
    {
      "nip": "198912272025212028",
      "index": 293,
      "timestamp": "2026-01-06 10:31:39",
      "status": "success"
    },
    {
      "nip": "198912312025212076",
      "index": 294,
      "timestamp": "2026-01-06 10:31:53",
      "status": "success"
    },
    {
      "nip": "199001022025211030",
      "index": 295,
      "timestamp": "2026-01-06 10:32:07",
      "status": "success"
    },
    {
      "nip": "199001042025212022",
      "index": 296,
      "timestamp": "2026-01-06 10:32:22",
      "status": "success"
    },
    {
      "nip": "199001112025211017",
      "index": 297,
      "timestamp": "2026-01-06 10:32:36",
      "status": "success"
    },
    {
      "nip": "199001152025211028",
      "index": 298,
      "timestamp": "2026-01-06 10:32:51",
      "status": "success"
    },
    {
      "nip": "199001162023211018",
      "index": 299,
      "timestamp": "2026-01-06 10:33:05",
      "status": "success"
    },
    {
      "nip": "199001242025211026",
      "index": 300,
      "timestamp": "2026-01-06 10:33:19",
      "status": "success"
    },
    {
      "nip": "199002212025211030",
      "index": 301,
      "timestamp": "2026-01-06 10:33:34",
      "status": "success"
    },
    {
      "nip": "199003082025212015",
      "index": 302,
      "timestamp": "2026-01-06 10:33:48",
      "status": "success"
    },
    {
      "nip": "199003142025212042",
      "index": 303,
      "timestamp": "2026-01-06 10:34:03",
      "status": "success"
    },
    {
      "nip": "199003172025212030",
      "index": 304,
      "timestamp": "2026-01-06 10:34:17",
      "status": "success"
    },
    {
      "nip": "199003282025211035",
      "index": 305,
      "timestamp": "2026-01-06 10:34:31",
      "status": "success"
    },
    {
      "nip": "199004102025211054",
      "index": 306,
      "timestamp": "2026-01-06 10:34:46",
      "status": "success"
    },
    {
      "nip": "199004132025212024",
      "index": 307,
      "timestamp": "2026-01-06 10:35:00",
      "status": "success"
    },
    {
      "nip": "199004182025211019",
      "index": 308,
      "timestamp": "2026-01-06 10:35:15",
      "status": "success"
    },
    {
      "nip": "199004212025211022",
      "index": 309,
      "timestamp": "2026-01-06 10:35:29",
      "status": "success"
    },
    {
      "nip": "199004212025211023",
      "index": 310,
      "timestamp": "2026-01-06 10:35:43",
      "status": "success"
    },
    {
      "nip": "199005052025211050",
      "index": 311,
      "timestamp": "2026-01-06 10:35:58",
      "status": "success"
    },
    {
      "nip": "199005052025211051",
      "index": 312,
      "timestamp": "2026-01-06 10:36:12",
      "status": "success"
    },
    {
      "nip": "199005092025211021",
      "index": 313,
      "timestamp": "2026-01-06 10:36:27",
      "status": "success"
    },
    {
      "nip": "199005112025212027",
      "index": 314,
      "timestamp": "2026-01-06 10:36:41",
      "status": "success"
    },
    {
      "nip": "199005172023211020",
      "index": 315,
      "timestamp": "2026-01-06 10:36:55",
      "status": "success"
    },
    {
      "nip": "199005212025211026",
      "index": 316,
      "timestamp": "2026-01-06 10:37:10",
      "status": "success"
    },
    {
      "nip": "199005232024211001",
      "index": 317,
      "timestamp": "2026-01-06 10:37:24",
      "status": "success"
    },
    {
      "nip": "199005242025211019",
      "index": 318,
      "timestamp": "2026-01-06 10:37:39",
      "status": "success"
    },
    {
      "nip": "199005282025212023",
      "index": 319,
      "timestamp": "2026-01-06 10:37:53",
      "status": "success"
    },
    {
      "nip": "199006142025211033",
      "index": 320,
      "timestamp": "2026-01-06 10:38:07",
      "status": "success"
    },
    {
      "nip": "199006232023211016",
      "index": 321,
      "timestamp": "2026-01-06 10:38:22",
      "status": "success"
    },
    {
      "nip": "199007042025212028",
      "index": 322,
      "timestamp": "2026-01-06 10:38:36",
      "status": "success"
    },
    {
      "nip": "199007072025211038",
      "index": 323,
      "timestamp": "2026-01-06 10:38:51",
      "status": "success"
    },
    {
      "nip": "199007152025212049",
      "index": 324,
      "timestamp": "2026-01-06 10:39:05",
      "status": "success"
    },
    {
      "nip": "199007222025211019",
      "index": 325,
      "timestamp": "2026-01-06 10:39:20",
      "status": "success"
    },
    {
      "nip": "199007222025212016",
      "index": 326,
      "timestamp": "2026-01-06 10:39:34",
      "status": "success"
    },
    {
      "nip": "199007282025211020",
      "index": 327,
      "timestamp": "2026-01-06 10:39:48",
      "status": "success"
    },
    {
      "nip": "199008022025212030",
      "index": 328,
      "timestamp": "2026-01-06 10:40:03",
      "status": "success"
    },
    {
      "nip": "199008052025212029",
      "index": 329,
      "timestamp": "2026-01-06 10:40:17",
      "status": "success"
    },
    {
      "nip": "199008052025212030",
      "index": 330,
      "timestamp": "2026-01-06 10:40:32",
      "status": "success"
    },
    {
      "nip": "199008082025212037",
      "index": 331,
      "timestamp": "2026-01-06 10:40:46",
      "status": "success"
    },
    {
      "nip": "199008252023211020",
      "index": 332,
      "timestamp": "2026-01-06 10:41:00",
      "status": "success"
    },
    {
      "nip": "199009102025211051",
      "index": 333,
      "timestamp": "2026-01-06 10:41:15",
      "status": "success"
    },
    {
      "nip": "199009202025211023",
      "index": 334,
      "timestamp": "2026-01-06 10:41:29",
      "status": "success"
    },
    {
      "nip": "199009202025212023",
      "index": 335,
      "timestamp": "2026-01-06 10:41:44",
      "status": "success"
    },
    {
      "nip": "199009202025212024",
      "index": 336,
      "timestamp": "2026-01-06 10:41:58",
      "status": "success"
    },
    {
      "nip": "199010092025212024",
      "index": 337,
      "timestamp": "2026-01-06 10:42:12",
      "status": "success"
    },
    {
      "nip": "199010242025211035",
      "index": 338,
      "timestamp": "2026-01-06 10:42:27",
      "status": "success"
    },
    {
      "nip": "199011012025211038",
      "index": 339,
      "timestamp": "2026-01-06 10:42:41",
      "status": "success"
    },
    {
      "nip": "199011022025211024",
      "index": 340,
      "timestamp": "2026-01-06 10:42:56",
      "status": "success"
    },
    {
      "nip": "199011052025212021",
      "index": 341,
      "timestamp": "2026-01-06 10:43:10",
      "status": "success"
    },
    {
      "nip": "199011092025212026",
      "index": 342,
      "timestamp": "2026-01-06 10:43:24",
      "status": "success"
    },
    {
      "nip": "199011222025211018",
      "index": 343,
      "timestamp": "2026-01-06 10:43:39",
      "status": "success"
    },
    {
      "nip": "199012022025211022",
      "index": 344,
      "timestamp": "2026-01-06 10:43:53",
      "status": "success"
    },
    {
      "nip": "199012062025212028",
      "index": 345,
      "timestamp": "2026-01-06 10:44:08",
      "status": "success"
    },
    {
      "nip": "199012102025211034",
      "index": 347,
      "timestamp": "2026-01-06 10:44:37",
      "status": "success"
    },
    {
      "nip": "199012142025211021",
      "index": 348,
      "timestamp": "2026-01-06 10:44:51",
      "status": "success"
    },
    {
      "nip": "199012182025211026",
      "index": 349,
      "timestamp": "2026-01-06 10:45:05",
      "status": "success"
    },
    {
      "nip": "199012212025211015",
      "index": 350,
      "timestamp": "2026-01-06 10:45:20",
      "status": "success"
    },
    {
      "nip": "199012222025212030",
      "index": 351,
      "timestamp": "2026-01-06 10:45:34",
      "status": "success"
    },
    {
      "nip": "199012302025212031",
      "index": 352,
      "timestamp": "2026-01-06 10:45:49",
      "status": "success"
    },
    {
      "nip": "199012312025211073",
      "index": 353,
      "timestamp": "2026-01-06 10:46:03",
      "status": "success"
    },
    {
      "nip": "199101072025212054",
      "index": 354,
      "timestamp": "2026-01-06 10:46:18",
      "status": "success"
    },
    {
      "nip": "199101102025212035",
      "index": 355,
      "timestamp": "2026-01-06 10:46:32",
      "status": "success"
    },
    {
      "nip": "199101162025212035",
      "index": 356,
      "timestamp": "2026-01-06 10:46:46",
      "status": "success"
    },
    {
      "nip": "199101252025212037",
      "index": 357,
      "timestamp": "2026-01-06 10:47:01",
      "status": "success"
    },
    {
      "nip": "199101312025212019",
      "index": 358,
      "timestamp": "2026-01-06 10:47:15",
      "status": "success"
    },
    {
      "nip": "199102062025211018",
      "index": 359,
      "timestamp": "2026-01-06 10:47:30",
      "status": "success"
    },
    {
      "nip": "199102062025211019",
      "index": 360,
      "timestamp": "2026-01-06 10:47:44",
      "status": "success"
    },
    {
      "nip": "199102152025211022",
      "index": 361,
      "timestamp": "2026-01-06 10:47:58",
      "status": "success"
    },
    {
      "nip": "199102262025211012",
      "index": 362,
      "timestamp": "2026-01-06 10:48:13",
      "status": "success"
    },
    {
      "nip": "199103062025211030",
      "index": 363,
      "timestamp": "2026-01-06 10:48:27",
      "status": "success"
    },
    {
      "nip": "199103072025212017",
      "index": 364,
      "timestamp": "2026-01-06 10:48:42",
      "status": "success"
    },
    {
      "nip": "199103092025212034",
      "index": 365,
      "timestamp": "2026-01-06 10:48:56",
      "status": "success"
    },
    {
      "nip": "199104032025212040",
      "index": 366,
      "timestamp": "2026-01-06 10:49:10",
      "status": "success"
    },
    {
      "nip": "199104052025211031",
      "index": 367,
      "timestamp": "2026-01-06 10:49:25",
      "status": "success"
    },
    {
      "nip": "199104062025212020",
      "index": 368,
      "timestamp": "2026-01-06 10:49:39",
      "status": "success"
    },
    {
      "nip": "199104152025212050",
      "index": 369,
      "timestamp": "2026-01-06 10:49:54",
      "status": "success"
    },
    {
      "nip": "199105012025212025",
      "index": 370,
      "timestamp": "2026-01-06 10:50:08",
      "status": "success"
    },
    {
      "nip": "199105092025212039",
      "index": 371,
      "timestamp": "2026-01-06 10:50:22",
      "status": "success"
    },
    {
      "nip": "199105102025211062",
      "index": 372,
      "timestamp": "2026-01-06 10:50:37",
      "status": "success"
    },
    {
      "nip": "199105172025211032",
      "index": 373,
      "timestamp": "2026-01-06 10:50:51",
      "status": "success"
    },
    {
      "nip": "199105232025211026",
      "index": 374,
      "timestamp": "2026-01-06 10:51:06",
      "status": "success"
    },
    {
      "nip": "199105252023211026",
      "index": 375,
      "timestamp": "2026-01-06 10:51:20",
      "status": "success"
    },
    {
      "nip": "199106052025211031",
      "index": 376,
      "timestamp": "2026-01-06 10:51:35",
      "status": "success"
    },
    {
      "nip": "199106062025211031",
      "index": 377,
      "timestamp": "2026-01-06 10:51:49",
      "status": "success"
    },
    {
      "nip": "199107042025211044",
      "index": 378,
      "timestamp": "2026-01-06 10:52:03",
      "status": "success"
    },
    {
      "nip": "199107112025211021",
      "index": 379,
      "timestamp": "2026-01-06 10:52:18",
      "status": "success"
    },
    {
      "nip": "199107122023211016",
      "index": 380,
      "timestamp": "2026-01-06 10:52:32",
      "status": "success"
    },
    {
      "nip": "199107292025212036",
      "index": 381,
      "timestamp": "2026-01-06 10:52:47",
      "status": "success"
    },
    {
      "nip": "199108052025212030",
      "index": 382,
      "timestamp": "2026-01-06 10:53:01",
      "status": "success"
    },
    {
      "nip": "199108102025211032",
      "index": 383,
      "timestamp": "2026-01-06 10:53:15",
      "status": "success"
    },
    {
      "nip": "199108132025211024",
      "index": 384,
      "timestamp": "2026-01-06 10:53:30",
      "status": "success"
    },
    {
      "nip": "199109082025211060",
      "index": 385,
      "timestamp": "2026-01-06 10:53:44",
      "status": "success"
    },
    {
      "nip": "199110102025212055",
      "index": 386,
      "timestamp": "2026-01-06 11:12:54",
      "status": "success"
    },
    {
      "nip": "199110122025212029",
      "index": 387,
      "timestamp": "2026-01-06 11:13:09",
      "status": "success"
    },
    {
      "nip": "199110242025211029",
      "index": 388,
      "timestamp": "2026-01-06 11:13:52",
      "status": "success"
    },
    {
      "nip": "199111102025212044",
      "index": 389,
      "timestamp": "2026-01-06 11:14:07",
      "status": "success"
    },
    {
      "nip": "199111172025212031",
      "index": 390,
      "timestamp": "2026-01-06 11:14:21",
      "status": "success"
    },
    {
      "nip": "199111192025211027",
      "index": 391,
      "timestamp": "2026-01-06 11:14:35",
      "status": "success"
    },
    {
      "nip": "199111212025211036",
      "index": 392,
      "timestamp": "2026-01-06 11:14:50",
      "status": "success"
    },
    {
      "nip": "199111282025211031",
      "index": 393,
      "timestamp": "2026-01-06 11:15:04",
      "status": "success"
    },
    {
      "nip": "199112012025212023",
      "index": 394,
      "timestamp": "2026-01-06 11:15:19",
      "status": "success"
    },
    {
      "nip": "199112142025211020",
      "index": 395,
      "timestamp": "2026-01-06 11:15:33",
      "status": "success"
    },
    {
      "nip": "199112172025211036",
      "index": 396,
      "timestamp": "2026-01-06 11:15:47",
      "status": "success"
    },
    {
      "nip": "199112182025211018",
      "index": 397,
      "timestamp": "2026-01-06 11:16:02",
      "status": "success"
    },
    {
      "nip": "199112292025211042",
      "index": 398,
      "timestamp": "2026-01-06 11:16:16",
      "status": "success"
    },
    {
      "nip": "199809182024211001",
      "index": 399,
      "timestamp": "2026-01-06 11:35:48",
      "status": "success"
    },
    {
      "nip": "199809232025212014",
      "index": 400,
      "timestamp": "2026-01-06 11:36:02",
      "status": "success"
    },
    {
      "nip": "199809272025212007",
      "index": 401,
      "timestamp": "2026-01-06 11:38:00",
      "status": "success"
    },
    {
      "nip": "199809302025212025",
      "index": 402,
      "timestamp": "2026-01-06 11:38:14",
      "status": "success"
    },
    {
      "nip": "199810032025212029",
      "index": 403,
      "timestamp": "2026-01-06 11:38:29",
      "status": "success"
    },
    {
      "nip": "199810142025211016",
      "index": 404,
      "timestamp": "2026-01-06 11:38:43",
      "status": "success"
    },
    {
      "nip": "199810222025211010",
      "index": 405,
      "timestamp": "2026-01-06 11:38:58",
      "status": "success"
    },
    {
      "nip": "199810222025211014",
      "index": 406,
      "timestamp": "2026-01-06 11:39:12",
      "status": "success"
    },
    {
      "nip": "199811152025211016",
      "index": 407,
      "timestamp": "2026-01-06 11:39:26",
      "status": "success"
    },
    {
      "nip": "199812162025212009",
      "index": 408,
      "timestamp": "2026-01-06 11:39:41",
      "status": "success"
    }
  ],
  "last_index": 408
}